utils_miget/__init__.py
utils_miget/calculations_miget.py
utils_miget/vq_plotter.py
utils_miget-1.9.4.dist-info/LICENSE.txt
utils_miget-1.9.4.dist-info/METADATA
utils_miget-1.9.4.dist-info/WHEEL
utils_miget-1.9.4.dist-info/top_level.txt
utils_miget-1.9.4.dist-info/RECORD
