Metadata-Version: 2.1
Name: utils-miget
Version: 1.9.4
Summary: Utilities to handle MIGET data
Home-page: UNKNOWN
Author: Mattia Busana
Author-email: mat.busana@gmail.com
License: UNKNOWN
Platform: UNKNOWN
Classifier: Development Status :: 2 - Pre-Alpha
Classifier: Intended Audience :: Science/Research
Classifier: Programming Language :: Python :: 3
Classifier: Operating System :: MacOS :: MacOS X
Classifier: Operating System :: Microsoft :: Windows
Requires-Python: >=3.7
License-File: LICENSE.txt
